setup.py
BiGa_distributions/Binomialdistribution.py
BiGa_distributions/Gaussiandistribution.py
BiGa_distributions/Generaldistribution.py
BiGa_distributions/__init__.py
BiGa_distributions.egg-info/PKG-INFO
BiGa_distributions.egg-info/SOURCES.txt
BiGa_distributions.egg-info/dependency_links.txt
BiGa_distributions.egg-info/not-zip-safe
BiGa_distributions.egg-info/top_level.txt