Metadata-Version: 1.0
Name: BiGa-distributions
Version: 1.2
Summary: Binomial and Gaussian distributions
Home-page: UNKNOWN
Author: Farha Haider
Author-email: farhahaider2017@gmail.com
License: UNKNOWN
Platform: UNKNOWN
